pyRedmineClient-1.0.0.dist-info/DESCRIPTION.rst
pyRedmineClient-1.0.0.dist-info/METADATA
pyRedmineClient-1.0.0.dist-info/RECORD
pyRedmineClient-1.0.0.dist-info/WHEEL
pyRedmineClient-1.0.0.dist-info/entry_points.txt
pyRedmineClient-1.0.0.dist-info/metadata.json
pyRedmineClient-1.0.0.dist-info/top_level.txt
redmine_cli/__init__.py
redmine_cli/redmine.py
