Metadata-Version: 2.0
Name: pyRedmineClient
Version: 1.0.0
Summary: CLI library to manage and operate all the entities of the service directory via HTTP
Home-page: https://github.com/palmerabollo/redmine-cli
Author: 4pf team
Author-email: guido.garciabernardo@telefonica.com, eduardo.alonsogarcia@telefonica.com
License: (C) Telefonica I+D
Platform: UNKNOWN
Classifier: Environment :: Console
Classifier: Intended Audience :: Developers
Classifier: License :: OSI Approved :: MIT License
Classifier: Operating System :: OS Independent
Classifier: Programming Language :: Python
Requires-Dist: docopt (==0.6.2)
Requires-Dist: requests (==2.17.3)
